MANIFEST.in
README.md
README.txt
setup.py
MiscUtils/Combinators.py
MiscUtils/DomHelpers.py
MiscUtils/FileMimeTypes.py
MiscUtils/Functions.py
MiscUtils/HttpSession.py
MiscUtils/MockHttpResources.py
MiscUtils/NetUtils.py
MiscUtils/ScanDirectories.py
MiscUtils/ScanFiles.py
MiscUtils/SuperGlobal.py
MiscUtils/TestUtils.py
MiscUtils/__init__.py
checklist/__init__.py
checklist/checklist_template.py
checklist/grid.py
checklist/gridmatch.py
checklist/minim_graph.py
checklist/mkminim.py
checklist/test/TestGridMatch.py
checklist/test/TestMkMinim.py
checklist/test/__init__.py
iaeval/__init__.py
iaeval/ro_eval_minim.py
iaeval/ro_minim.py
iaeval/test/TestEvalChecklist.py
iaeval/test/TestEvalQueryMatch.py
iaeval/test/TestMinimAccess.py
iaeval/test/TestMinimAccess2.py
iaeval/test/__init__.py
iaeval/test/config/README
ro_manager.egg-info/PKG-INFO
ro_manager.egg-info/SOURCES.txt
ro_manager.egg-info/dependency_links.txt
ro_manager.egg-info/entry_points.txt
ro_manager.egg-info/not-zip-safe
ro_manager.egg-info/requires.txt
ro_manager.egg-info/top_level.txt
rocommand/ROSRS_Session.py
rocommand/__init__.py
rocommand/ro.py
rocommand/ro_annotation.py
rocommand/ro_command.py
rocommand/ro_evo.py
rocommand/ro_manifest.py
rocommand/ro_metadata.py
rocommand/ro_namespaces.py
rocommand/ro_prefixes.py
rocommand/ro_remote_metadata.py
rocommand/ro_rosrs_sync.py
rocommand/ro_settings.py
rocommand/ro_uriutils.py
rocommand/ro_utils.py
rocommand/test/CurrentDirectoryContext.py
rocommand/test/RunRoManagerTests.py
rocommand/test/StdoutContext.py
rocommand/test/TestAll.py
rocommand/test/TestAnnotationUtils.py
rocommand/test/TestAnnotations.py
rocommand/test/TestBasicCommands.py
rocommand/test/TestConfig.py
rocommand/test/TestEvo.py
rocommand/test/TestEvoCommands.py
rocommand/test/TestLinks.py
rocommand/test/TestManifest.py
rocommand/test/TestROEVOSupport.py
rocommand/test/TestROMetadata.py
rocommand/test/TestROSRSMetadata.py
rocommand/test/TestROSRS_Session.py
rocommand/test/TestROSupport.py
rocommand/test/TestRemoteROMetadata.py
rocommand/test/TestRosrsSync.py
rocommand/test/TestSparqlQueries.py
rocommand/test/TestSyncCommands.py
rocommand/test/__init__.py
rocommand/test/config/.ro_config
rocommand/test/config/README
