Metadata-Version: 1.0
Name: ro-manager
Version: 0.2.17
Summary: Research Object manager (command line tool)
Home-page: https://github.com/wf4ever/ro-manager
Author: Graham Klyne
Author-email: gk-pypi@ninebynine.org
License: MIT
Platform: UNKNOWN
Classifier: Development Status :: 3 - Alpha
Classifier: Environment :: Console
Classifier: Environment :: Web Environment
Classifier: Intended Audience :: Developers
Classifier: License :: OSI Approved :: MIT License
Classifier: Operating System :: OS Independent
Classifier: Programming Language :: Python
